Metadata-Version: 2.1
Name: snm-build
Version: 0.0.4
Summary: Building and release project
Home-page: UNKNOWN
Author-email: serheos@gmail.com
License: UNKNOWN
Platform: UNKNOWN
